{
  "parent": "minecraft:recipes/root",
  "requirements": [
    [
      "has_glow_berries",
      "has_the_recipe"
    ]
  ],
  "criteria": {
    "has_glow_berries": {
      "trigger": "minecraft:inventory_changed",
      "conditions": {
        "items": [
          {
            "item": "minecraft:glow_berries"
          }
        ]
      }
    },
    "has_the_recipe": {
      "trigger": "minecraft:recipe_unlocked",
      "conditions": {
        "recipe": "aureusstuff:glow_berry_goggles"
      }
    }
  },
  "rewards": {
    "recipes": [
      "aureusstuff:glow_berry_goggles"
    ]
  }
}